{"images":{"image_id":833709,"farm_id":"AIF001","crops_id":"C11_L01_01","crops":"상추","kind_type":"로메인","file_path":"/cropsImages/L/L01/AIF001/C11","fname":"C11_L01_01_003_220119181109.jpg","fext":"jpg","width":"1285","height":"723","create_date":"2022-01-20","date_captured":"2022-01-19 18:11:09","growth_stage":"수확기","leaf":"1","plant_body":"1"},"envrionments":[{"farm_id":"AIF001","receive_date":"2022-01-19 18:10:16","id":0,"ti_value":"24.0","hi_value":"61.0","ci_value":"224","ir_value":"29","tl_value":"22.9","ei_value":"0.18","pl_value":"4.0"},{"farm_id":"AIF001","receive_date":"2022-01-19 18:06:17","id":1,"ti_value":"24.0","hi_value":"61.0","ci_value":"223","ir_value":"9","tl_value":"22.9","ei_value":"0.18","pl_value":"4.0"}],"growth_index":{"corps_id":"C11_L01_01","measured_date":null,"stem_length":null,"leaf_cnt":null,"leaf_width":null,"leaf_length":null,"stem_thick":null,"fr_weight":null},"etc_infor":{"corps_id":"C11_L01_01","create_date":"","inform":""},"annotations":[{"segmentation":[33.5,69.52,1239.91,69.52,1239.91,695.16,33.5,695.16],"area":754778.35,"bbox":[33.5,69.52,1206.41,625.64],"isCrowd":0,"id":0,"image_id":833709,"category_id":0},{"segmentation":[494.88,480.88,953.52,480.88,953.52,694.52,494.88,694.52],"area":97983.84,"bbox":[494.88,480.88,458.64,213.64],"isCrowd":0,"id":1,"image_id":833709,"category_id":1},{"segmentation":[444.88,72.7,762.61,72.7,762.61,465.89,444.88,465.89],"area":124928.25,"bbox":[444.88,72.7,317.73,393.19],"isCrowd":0,"id":2,"image_id":833709,"category_id":2},{"segmentation":[648.52,342.7,809.89,342.7,809.89,487.7,648.52,487.7],"area":23398.65,"bbox":[648.52,342.7,161.37,145],"isCrowd":0,"id":3,"image_id":833709,"category_id":3},{"segmentation":[670.79,249.52,1240.33,249.52,1240.33,494.84,670.79,494.84],"area":139722,"bbox":[670.79,249.52,569.55,245.32],"isCrowd":0,"id":4,"image_id":833709,"category_id":4}],"licenses":[{"id":1,"name":"CCMediaService","url":""}],"categories":[{"id":0,"name":"주","supercategory":"none"},{"id":1,"name":"잎","supercategory":"none"},{"id":2,"name":"잎","supercategory":"none"},{"id":3,"name":"잎","supercategory":"none"},{"id":4,"name":"잎","supercategory":"none"}]}