{"images":{"image_id":853342,"farm_id":"AIF001","crops_id":"C11_L01_01","crops":"상추","kind_type":"로메인","file_path":"/cropsImages/L/L01/AIF001/C11","fname":"C11_L01_01_006_220121151109.jpg","fext":"jpg","width":"1693","height":"1224","create_date":"2022-01-24","date_captured":"2022-01-21 15:11:09","growth_stage":"수확기","leaf":"1","plant_body":"1"},"envrionments":[{"farm_id":"AIF001","receive_date":"2022-01-21 15:10:19","id":0,"ti_value":"24.0","hi_value":"61.0","ci_value":"355","ir_value":"118","tl_value":"14.9","ei_value":"0.18","pl_value":"5.8"},{"farm_id":"AIF001","receive_date":"2022-01-21 15:06:19","id":1,"ti_value":"24.0","hi_value":"62.0","ci_value":"357","ir_value":"93","tl_value":"15.0","ei_value":"0.18","pl_value":"5.8"}],"growth_index":{"corps_id":"C11_L01_01","measured_date":null,"stem_length":null,"leaf_cnt":null,"leaf_width":null,"leaf_length":null,"stem_thick":null,"fr_weight":null},"etc_infor":{"corps_id":"C11_L01_01","create_date":"","inform":""},"annotations":[{"segmentation":[30.4,57.45,1625.91,57.45,1625.91,1198.66,30.4,1198.66],"area":1820811.96,"bbox":[30.4,57.45,1595.51,1141.21],"isCrowd":0,"id":0,"image_id":853342,"category_id":0},{"segmentation":[123.7,514.71,940.13,514.71,940.13,1199.05,123.7,1199.05],"area":558715.7,"bbox":[123.7,514.71,816.43,684.34],"isCrowd":0,"id":1,"image_id":853342,"category_id":1},{"segmentation":[537.35,475.83,784.62,475.83,784.62,732.46,537.35,732.46],"area":63456.9,"bbox":[537.35,475.83,247.27,256.63],"isCrowd":0,"id":2,"image_id":853342,"category_id":2},{"segmentation":[692.86,474.28,829.74,474.28,829.74,712.25,692.86,712.25],"area":32573.33,"bbox":[692.86,474.28,136.88,237.97],"isCrowd":0,"id":3,"image_id":853342,"category_id":3},{"segmentation":[806.37,345.19,1324.21,345.19,1324.21,800.9,806.37,800.9],"area":235984.86,"bbox":[806.37,345.19,517.84,455.71],"isCrowd":0,"id":4,"image_id":853342,"category_id":4},{"segmentation":[123.7,198.99,616.29,198.99,616.29,730.91,123.7,730.91],"area":262018.47,"bbox":[123.7,198.99,492.59,531.92],"isCrowd":0,"id":5,"image_id":853342,"category_id":5}],"licenses":[{"id":1,"name":"CCMediaService","url":""}],"categories":[{"id":0,"name":"주","supercategory":"none"},{"id":1,"name":"잎","supercategory":"none"},{"id":2,"name":"잎","supercategory":"none"},{"id":3,"name":"잎","supercategory":"none"},{"id":4,"name":"잎","supercategory":"none"},{"id":5,"name":"잎","supercategory":"none"}]}