{"images":{"image_id":490853,"farm_id":"AIF003","crops_id":"C17_L01_01","crops":"상추","kind_type":"햇살적축면","file_path":"/cropsImages/L/L01/AIF003/C17","fname":"C17_L01_01_005_211114140159.jpg","fext":"jpg","width":"1271","height":"1047","create_date":"2021-11-16","date_captured":"2021-11-14 14:01:59","growth_stage":"수확기","leaf":"0","plant_body":"0"},"envrionments":[{"farm_id":"AIF003","receive_date":"2021-11-14 14:01:08","id":0,"ti_value":"23.0","hi_value":"53.0","ci_value":"359","ir_value":"0","tl_value":"22.9","ei_value":"0.28","pl_value":"3.7"},{"farm_id":"AIF003","receive_date":"2021-11-14 13:57:09","id":1,"ti_value":"22.0","hi_value":"58.0","ci_value":"359","ir_value":"186","tl_value":"22.9","ei_value":"0.28","pl_value":"3.7"}],"growth_index":{"corps_id":"C17_L01_01","measured_date":null,"stem_length":null,"leaf_cnt":null,"leaf_width":null,"leaf_length":null,"stem_thick":null,"fr_weight":null},"etc_infor":{"corps_id":"C17_L01_01","create_date":"","inform":""},"annotations":[{"segmentation":[271.07,154.89,1116.25,154.89,1116.25,869.46,271.07,869.46],"area":603940.27,"bbox":[271.07,154.89,845.18,714.57],"isCrowd":0,"id":0,"image_id":490853,"category_id":0}],"licenses":[{"id":1,"name":"CCMediaService","url":""}],"categories":[{"id":0,"name":"주","supercategory":"none"}]}