{"images":{"image_id":490988,"farm_id":"AIF003","crops_id":"C17_L01_01","crops":"상추","kind_type":"햇살적축면","file_path":"/cropsImages/L/L01/AIF003/C17","fname":"C17_L01_01_002_211112170159.jpg","fext":"jpg","width":"1663","height":"1360","create_date":"2021-11-16","date_captured":"2021-11-12 17:01:59","growth_stage":"수확기","leaf":"1","plant_body":"0"},"envrionments":[{"farm_id":"AIF003","receive_date":"2021-11-12 17:00:59","id":0,"ti_value":"22.0","hi_value":"49.0","ci_value":"380","ir_value":"263","tl_value":"22.7","ei_value":"0.27","pl_value":"3.7"},{"farm_id":"AIF003","receive_date":"2021-11-12 16:56:56","id":1,"ti_value":"23.0","hi_value":"53.0","ci_value":"385","ir_value":"198","tl_value":null,"ei_value":null,"pl_value":null}],"growth_index":{"corps_id":"C17_L01_01","measured_date":null,"stem_length":null,"leaf_cnt":null,"leaf_width":null,"leaf_length":null,"stem_thick":null,"fr_weight":null},"etc_infor":{"corps_id":"C17_L01_01","create_date":"","inform":""},"annotations":[{"segmentation":[182.77,138.31,1566.05,138.31,1566.05,1111.85,182.77,1111.85],"area":1346692.24,"bbox":[182.77,138.31,1383.28,973.55],"isCrowd":0,"id":0,"image_id":490988,"category_id":0},{"segmentation":[227.69,345.34,983.23,345.34,983.23,1113.05,227.69,1113.05],"area":580035.61,"bbox":[227.69,345.34,755.54,767.71],"isCrowd":0,"id":1,"image_id":490988,"category_id":1},{"segmentation":[960.47,199.99,1566.91,199.99,1566.91,928.59,960.47,928.59],"area":441852.18,"bbox":[960.47,199.99,606.44,728.6],"isCrowd":0,"id":2,"image_id":490988,"category_id":2},{"segmentation":[648.44,135.44,1059.06,135.44,1059.06,731.71,648.44,731.71],"area":244840.38,"bbox":[648.44,135.44,410.62,596.27],"isCrowd":0,"id":3,"image_id":490988,"category_id":3},{"segmentation":[180.4,241.95,706.15,241.95,706.15,599.38,180.4,599.38],"area":187918.82,"bbox":[180.4,241.95,525.75,357.43],"isCrowd":0,"id":4,"image_id":490988,"category_id":4}],"licenses":[{"id":1,"name":"CCMediaService","url":""}],"categories":[{"id":0,"name":"주","supercategory":"none"},{"id":1,"name":"잎","supercategory":"none"},{"id":2,"name":"잎","supercategory":"none"},{"id":3,"name":"잎","supercategory":"none"},{"id":4,"name":"잎","supercategory":"none"}]}