{"images":{"image_id":456338,"farm_id":"AIF009","crops_id":"C30_L01_01_05","crops":"상추","kind_type":"로메인","file_path":"/cropsImages/L/L01/AIF009/C30","fname":"C30_L01_01_05_002_210903214907.jpg","fext":"jpg","width":"2545","height":"2256","create_date":"2021-11-10","date_captured":"2021-09-03 21:49:07","growth_stage":"수확기","leaf":"1","plant_body":"0"},"envrionments":[{"farm_id":"AIF009","receive_date":"2021-09-03 21:48:22","id":0,"ti_value":"22.0","hi_value":"79.0","ci_value":"721","ir_value":"0","tl_value":"23.4","ei_value":"0.21","pl_value":"7.7"},{"farm_id":"AIF009","receive_date":"2021-09-03 21:44:23","id":1,"ti_value":"22.0","hi_value":"78.0","ci_value":"721","ir_value":"0","tl_value":"23.3","ei_value":"0.21","pl_value":"7.7"}],"growth_index":{"corps_id":"C30_L01_01_05","measured_date":null,"stem_length":null,"leaf_cnt":null,"leaf_width":null,"leaf_length":null,"stem_thick":null,"fr_weight":null},"etc_infor":{"corps_id":"C30_L01_01_05","create_date":"","inform":""},"annotations":[{"segmentation":[40.21,240.78,2471.52,240.78,2471.52,2174.02,40.21,2174.02],"area":4700305.74,"bbox":[40.21,240.78,2431.31,1933.24],"isCrowd":0,"id":0,"image_id":456338,"category_id":0},{"segmentation":[585.01,1188.35,1496.06,1188.35,1496.06,2174.02,585.01,2174.02],"area":897994.65,"bbox":[585.01,1188.35,911.05,985.67],"isCrowd":0,"id":1,"image_id":456338,"category_id":1},{"segmentation":[1355.51,933.94,2472.81,933.94,2472.81,1452.32,1355.51,1452.32],"area":579185.97,"bbox":[1355.51,933.94,1117.3,518.38],"isCrowd":0,"id":2,"image_id":456338,"category_id":2},{"segmentation":[1062.36,684.71,1379.32,684.71,1379.32,1181.02,1062.36,1181.02],"area":157310.41,"bbox":[1062.36,684.71,316.96,496.31],"isCrowd":0,"id":3,"image_id":456338,"category_id":3}],"licenses":[{"id":1,"name":"CCMediaService","url":""}],"categories":[{"id":0,"name":"주","supercategory":"none"},{"id":1,"name":"잎","supercategory":"none"},{"id":2,"name":"잎","supercategory":"none"},{"id":3,"name":"잎","supercategory":"none"}]}