{"images":{"image_id":833733,"farm_id":"AIF001","crops_id":"C11_L01_01","crops":"상추","kind_type":"로메인","file_path":"/cropsImages/L/L01/AIF001/C11","fname":"C11_L01_01_003_220120081109.jpg","fext":"jpg","width":"1257","height":"764","create_date":"2022-01-20","date_captured":"2022-01-20 08:11:09","growth_stage":"수확기","leaf":"1","plant_body":"1"},"envrionments":[{"farm_id":"AIF001","receive_date":"2022-01-20 08:10:33","id":0,"ti_value":"24.0","hi_value":"64.0","ci_value":"281","ir_value":"25","tl_value":"20.9","ei_value":"0.18","pl_value":"3.9"},{"farm_id":"AIF001","receive_date":"2022-01-20 08:06:33","id":1,"ti_value":"24.0","hi_value":"63.0","ci_value":"288","ir_value":"0","tl_value":"21.0","ei_value":"0.18","pl_value":"3.9"}],"growth_index":{"corps_id":"C11_L01_01","measured_date":null,"stem_length":null,"leaf_cnt":null,"leaf_width":null,"leaf_length":null,"stem_thick":null,"fr_weight":null},"etc_infor":{"corps_id":"C11_L01_01","create_date":"","inform":""},"annotations":[{"segmentation":[29.5,62.7,1250.91,62.7,1250.91,730.89,29.5,730.89],"area":816133.94,"bbox":[29.5,62.7,1221.41,668.19],"isCrowd":0,"id":0,"image_id":833733,"category_id":0},{"segmentation":[704.43,304.97,1250.8,304.97,1250.8,508.02,704.43,508.02],"area":110940.42,"bbox":[704.43,304.97,546.37,203.05],"isCrowd":0,"id":1,"image_id":833733,"category_id":1},{"segmentation":[443.06,471.79,930.33,471.79,930.33,731.34,443.06,731.34],"area":126470.92,"bbox":[443.06,471.79,487.27,259.55],"isCrowd":0,"id":2,"image_id":833733,"category_id":2},{"segmentation":[129.43,458.16,533.52,458.16,533.52,660.44,129.43,660.44],"area":81739.32,"bbox":[129.43,458.16,404.09,202.28],"isCrowd":0,"id":3,"image_id":833733,"category_id":3},{"segmentation":[28.97,62.7,468.97,62.7,468.97,306.66,28.97,306.66],"area":107342.4,"bbox":[28.97,62.7,440,243.96],"isCrowd":0,"id":4,"image_id":833733,"category_id":4}],"licenses":[{"id":1,"name":"CCMediaService","url":""}],"categories":[{"id":0,"name":"주","supercategory":"none"},{"id":1,"name":"잎","supercategory":"none"},{"id":2,"name":"잎","supercategory":"none"},{"id":3,"name":"잎","supercategory":"none"},{"id":4,"name":"잎","supercategory":"none"}]}