{"images":{"image_id":629988,"farm_id":"AIF003","crops_id":"C29_L04_01","crops":"상추","kind_type":"로메인","file_path":"/cropsImages/L/L04/AIF003/C29","fname":"C29_L04_01_007_211219142117.jpg","fext":"jpg","width":"1538","height":"1204","create_date":"2021-12-20","date_captured":"2021-12-19 14:21:17","growth_stage":"수확기","leaf":"1","plant_body":"1"},"envrionments":[{"farm_id":"AIF003","receive_date":"2021-12-19 14:21:06","id":0,"ti_value":"22.0","hi_value":"57.0","ci_value":"307","ir_value":"162","tl_value":"22.3","ei_value":"0.23","pl_value":"3.8"},{"farm_id":"AIF003","receive_date":"2021-12-19 14:17:06","id":1,"ti_value":"22.0","hi_value":"57.0","ci_value":"312","ir_value":"0","tl_value":"22.4","ei_value":"0.23","pl_value":"3.8"}],"growth_index":{"corps_id":"C29_L04_01","measured_date":null,"stem_length":null,"leaf_cnt":null,"leaf_width":null,"leaf_length":null,"stem_thick":null,"fr_weight":null},"etc_infor":{"corps_id":"C29_L04_01","create_date":"","inform":""},"annotations":[{"segmentation":[198.44,107.12,1104.54,107.12,1104.54,969.25,198.44,969.25],"area":781175.99,"bbox":[198.44,107.12,906.1,862.13],"isCrowd":0,"id":0,"image_id":629988,"category_id":0},{"segmentation":[643.14,560.6,761.78,560.6,761.78,628.27,643.14,628.27],"area":8028.36,"bbox":[643.14,560.6,118.64,67.67],"isCrowd":0,"id":1,"image_id":629988,"category_id":1},{"segmentation":[720.48,386.59,877.79,386.59,877.79,622.99,720.48,622.99],"area":37188.08,"bbox":[720.48,386.59,157.31,236.4],"isCrowd":0,"id":2,"image_id":629988,"category_id":2},{"segmentation":[574.59,564.12,911.19,564.12,911.19,775.92,574.59,775.92],"area":71291.88,"bbox":[574.59,564.12,336.6,211.8],"isCrowd":0,"id":3,"image_id":629988,"category_id":3},{"segmentation":[335.54,325.07,745.96,325.07,745.96,630.02,335.54,630.02],"area":125157.57,"bbox":[335.54,325.07,410.42,304.95],"isCrowd":0,"id":4,"image_id":629988,"category_id":4},{"segmentation":[637.87,108.88,948.1,108.88,948.1,575.54,637.87,575.54],"area":144771.93,"bbox":[637.87,108.88,310.23,466.66],"isCrowd":0,"id":5,"image_id":629988,"category_id":5}],"licenses":[{"id":1,"name":"CCMediaService","url":""}],"categories":[{"id":0,"name":"주","supercategory":"none"},{"id":1,"name":"잎","supercategory":"none"},{"id":2,"name":"잎","supercategory":"none"},{"id":3,"name":"잎","supercategory":"none"},{"id":4,"name":"잎","supercategory":"none"},{"id":5,"name":"잎","supercategory":"none"}]}