{"images":{"image_id":456024,"farm_id":"AIF009","crops_id":"C30_L01_01_05","crops":"상추","kind_type":"로메인","file_path":"/cropsImages/L/L01/AIF009/C30","fname":"C30_L01_01_05_002_210902084907.jpg","fext":"jpg","width":"2334","height":"2251","create_date":"2021-11-10","date_captured":"2021-09-02 08:49:07","growth_stage":"수확기","leaf":"1","plant_body":"0"},"envrionments":[{"farm_id":"AIF009","receive_date":"2021-09-02 08:48:36","id":0,"ti_value":"22.0","hi_value":"81.0","ci_value":"612","ir_value":"0","tl_value":"22.8","ei_value":"0.18","pl_value":"7.9"},{"farm_id":"AIF009","receive_date":"2021-09-02 08:44:37","id":1,"ti_value":"22.0","hi_value":"81.0","ci_value":"615","ir_value":"0","tl_value":"22.9","ei_value":"0.18","pl_value":"7.9"}],"growth_index":{"corps_id":"C30_L01_01_05","measured_date":null,"stem_length":null,"leaf_cnt":null,"leaf_width":null,"leaf_length":null,"stem_thick":null,"fr_weight":null},"etc_infor":{"corps_id":"C30_L01_01_05","create_date":"","inform":""},"annotations":[{"segmentation":[215.81,272.44,2115.22,272.44,2115.22,2181.82,215.81,2181.82],"area":3626695.46,"bbox":[215.81,272.44,1899.41,1909.38],"isCrowd":0,"id":0,"image_id":456024,"category_id":0},{"segmentation":[1127.78,960.73,1356.72,960.73,1356.72,1274.65,1127.78,1274.65],"area":71868.84,"bbox":[1127.78,960.73,228.94,313.92],"isCrowd":0,"id":1,"image_id":456024,"category_id":1},{"segmentation":[706.01,470.42,1192.08,470.42,1192.08,1272.8,706.01,1272.8],"area":390012.84,"bbox":[706.01,470.42,486.07,802.38],"isCrowd":0,"id":2,"image_id":456024,"category_id":2},{"segmentation":[1188.82,879.32,2104.05,879.32,2104.05,1492.97,1188.82,1492.97],"area":561630.88,"bbox":[1188.82,879.32,915.23,613.65],"isCrowd":0,"id":3,"image_id":456024,"category_id":3},{"segmentation":[478.48,1266.02,1401.11,1266.02,1401.11,2183.3,478.48,2183.3],"area":846310.04,"bbox":[478.48,1266.02,922.63,917.28],"isCrowd":0,"id":4,"image_id":456024,"category_id":4}],"licenses":[{"id":1,"name":"CCMediaService","url":""}],"categories":[{"id":0,"name":"주","supercategory":"none"},{"id":1,"name":"잎","supercategory":"none"},{"id":2,"name":"잎","supercategory":"none"},{"id":3,"name":"잎","supercategory":"none"},{"id":4,"name":"잎","supercategory":"none"}]}