{"images":{"image_id":728180,"farm_id":"AIF001","crops_id":"C26_L04_01","crops":"상추","kind_type":"햇살적축면","file_path":"/cropsImages/L/L04/AIF001/C26","fname":"C26_L04_01_008_211216084457.jpg","fext":"jpg","width":"1634","height":"1636","create_date":"2022-01-04","date_captured":"2021-12-16 08:44:57","growth_stage":"수확기","leaf":"1","plant_body":"1"},"envrionments":[{"farm_id":"AIF001","receive_date":"2021-12-16 08:44:32","id":0,"ti_value":"24.0","hi_value":"63.0","ci_value":"310","ir_value":"17","tl_value":"21.1","ei_value":"0.19","pl_value":"4.1"},{"farm_id":"AIF001","receive_date":"2021-12-16 08:39:20","id":1,"ti_value":"24.0","hi_value":"63.0","ci_value":"312","ir_value":"77","tl_value":"21.2","ei_value":"0.19","pl_value":"4.1"}],"growth_index":{"corps_id":"C26_L04_01","measured_date":null,"stem_length":null,"leaf_cnt":null,"leaf_width":null,"leaf_length":null,"stem_thick":null,"fr_weight":null},"etc_infor":{"corps_id":"C26_L04_01","create_date":"","inform":""},"annotations":[{"segmentation":[178.12,92.07,1433.44,92.07,1433.44,1581.89,178.12,1581.89],"area":1870200.84,"bbox":[178.12,92.07,1255.32,1489.82],"isCrowd":0,"id":0,"image_id":728180,"category_id":0},{"segmentation":[452.15,647.59,1342.28,647.59,1342.28,1582.33,452.15,1582.33],"area":832040.11,"bbox":[452.15,647.59,890.13,934.74],"isCrowd":0,"id":1,"image_id":728180,"category_id":1}],"licenses":[{"id":1,"name":"CCMediaService","url":""}],"categories":[{"id":0,"name":"주","supercategory":"none"},{"id":1,"name":"잎","supercategory":"none"}]}